dqdl.py
dqdl-0.2.0.dist-info/entry_points.txt
dqdl-0.2.0.dist-info/WHEEL
dqdl-0.2.0.dist-info/METADATA
dqdl-0.2.0.dist-info/RECORD
