Metadata-Version: 2.1
Name: dqdl
Version: 0.2.0
Summary: Dune query result downloader
Author-email: Eugene Kim <ek@karma3labs.com>
Requires-Python: >=3.12
Classifier: Development Status :: 3 - Alpha
Classifier: License :: OSI Approved :: MIT License
Classifier: Programming Language :: Python :: 3
Requires-Dist: dune-client>=1.7
Requires-Dist: python-dotenv>=1.0
Requires-Dist: pandas>=2.2
Requires-Dist: pyarrow>=17.0
Requires-Dist: passarg>=0.1.0
Requires-Dist: iso8601>=2.0.0
Project-URL: Homepage, https://github.com/Karma3Labs/dqdl
Project-URL: Issues, https://github.com/Karma3Labs/dqdl/issues
Project-URL: Repository, https://github.com/Karma3Labs/dqdl.git
